Part2/reg_file.v
/*
Authers     : WIJERATHNA I.M.K.D.I.     e19446@eng.pdn.ac.lk
              DISSANAYAKE D.M.I.G.      e19090@eng.pdn.ac.lk
Lab         : Lab 5 part 2
              reg_file.v
Last Updated: Wednesday, May 10, 2023 10:27:08 AM
*/

// Register File module to store output values from ALU
module reg_file(IN,OUT1,OUT2,INADDRESS,OUT1ADDRESS,OUT2ADDRESS, WRITE, CLK, RESET) ;
   
    //declaring ports

    //data input ports
    input[7:0] IN;
    //data output ports
    output[7:0] OUT1;
    output[7:0] OUT2;
    // address ports
    input[2:0] INADDRESS;
    input[2:0] OUT1ADDRESS;
    input[2:0] OUT2ADDRESS;
    //control input ports
    input WRITE;
    // clock signal and reset signal
    input CLK;
    input RESET;
   

    //declaring a register array(8*8)
    reg[7:0] REGISTER[0:7];

    /* $$$$$$$$$$$$$$$$$$$$$$$$$$$$$$$$$$$$$$$$$$$$$$$$$$$$$$$$$$$$$$$$$$$$$$$$$$$$$$$$$$$$$$$
         REGISTER READING OPERATION 
         --------------------------

         1. Reading the values in REGISTER specified by the provided addresses asynchronously
         2. The values are loaded onto OUT1 and OUT2
         3. Artificial delays of two time  units (#2) included

       $$$$$$$$$$$$$$$$$$$$$$$$$$$$$$$$$$$$$$$$$$$$$$$$$$$$$$$$$$$$$$$$$$$$$$$$$$$$$$$$$$$$$$$$*/
    assign #2 OUT1 = REGISTER[OUT1ADDRESS];
    assign #2 OUT2 = REGISTER[OUT2ADDRESS];

    
    /* $$$$$$$$$$$$$$$$$$$$$$$$$$$$$$$$$$$$$$$$$$$$$$$$$$$$$$$$$$$$$$$$$$$$$$$$$$$$$$$$$$$$$$$
         REGISTER WRITING OPERATION 
         --------------------------

         1. Positive edge triggerd with the clock pulse synchronously
         2. If RESET is enabled reset all the values of the REGISTER
         3. Else if WRITEENABLE wirte the data values into the REGISTER

       $$$$$$$$$$$$$$$$$$$$$$$$$$$$$$$$$$$$$$$$$$$$$$$$$$$$$$$$$$$$$$$$$$$$$$$$$$$$$$$$$$$$$$$$*/
    
    integer i; //parameter to iterate through the REGISTER

    // begin the continous loop at the positive edge of a clock pulse
    always @(posedge CLK)
          begin
          // if RESET is enabled Reset all the values in REGISTER
          // (Replace all values in REGISTER by 0)
          if (RESET)
               begin
               #1 // Artificial delay of one time unit
               
               for (i=0;i<8;i=i+1)
                    begin
                    REGISTER[i]<=0;
                    end
               end

          //else if check WRITEENABLE
          // if it is enabled write data values
          else
               begin
               if (WRITE)
                    begin
                    #1 // Artificial delay of one time unit
                    REGISTER[INADDRESS] <= IN;
                    end
               end
          end
//end the module
endmodule

/*
//Test values
module stimulus;
    //data input registers
    reg [7:0] IN;
    // address registers 
    reg [2:0] INADDRESS;
    reg [2:0] OUT1ADDRESS;
    reg [2:0] OUT2ADDRESS;
    //control input ports
    reg WRITEENABLE;
    // clock signal and reset signal
    reg CLK;
    reg RESET;
     //data output registers
    wire [7:0] OUT1;
    wire [7:0] OUT2;

    //calling the alu module
    reg_file   test(IN,OUT1,OUT2,INADDRESS,OUT1ADDRESS,OUT2ADDRESS, WRITEENABLE, CLK, RESET) ;

    initial begin
        //testing 
        // initial CLOCK signal = 1
        CLK = 1'b1; 
        // initial RESET to 0

        // generating files for GTK Wave
        $dumpfile("reg_file_wavedata.vcd");
	   $dumpvars(0, stimulus);
        
        $display("%b ,  %b", CLK, IN);

        RESET = 1'b1;
        WRITEENABLE= 1'b0;

        
        $display("%b ,  %b", CLK, IN);

        #4
       
        RESET = 1'b0;
        WRITEENABLE = 1'b1;
     
        
        $display("%b ,  %b", CLK, IN);

        #5
        INADDRESS = 3'd2;
        IN = 8'd50;
        
        $display("%b ,  %b", CLK, IN);
        
        #5
        WRITEENABLE = 1'b0;
        INADDRESS = 3'd2;
        IN = 8'd43;

        
        $display("%b ,  %b", CLK, IN);
        
        #5
        WRITEENABLE = 1'b1;
        INADDRESS = 3'd2;
        IN = 8'd43;

        
        $display("%b ,  %b", CLK, IN);
        #5
        WRITEENABLE = 1'b1;
          
        #5  
        OUT1ADDRESS= 3b'1;
        
        WRITEENABLE = 1'b0;

        $finish;
        
     end

     // generating the clock signal continuously
     always
          #5 CLK =~CLK;

endmodule
*/

Part2/reg_file_tb.v
// Computer Architecture (CO224) - Lab 05
// Design: Register File of Simple Processor
// Author: Kisaru Liyanage

module reg_file_tb;
    
    reg [7:0] WRITEDATA;
    reg [2:0] WRITEREG, READREG1, READREG2;
    reg CLK, RESET, WRITEENABLE; 
    wire [7:0] REGOUT1, REGOUT2;
    
    reg_file myregfile(WRITEDATA, REGOUT1, REGOUT2, WRITEREG, READREG1, READREG2, WRITEENABLE, CLK, RESET);
       
    initial
    begin
        CLK = 1'b1;
        
        // generate files needed to plot the waveform using GTKWave
        $dumpfile("reg_file_wavedata.vcd");
		$dumpvars(0, reg_file_tb);
        
        // assign values with time to input signals to see output 
        RESET = 1'b0;
        WRITEENABLE = 1'b0;
        
        #4
        RESET = 1'b1;
        READREG1 = 3'd0;
        READREG2 = 3'd4;
        
        #6
        RESET = 1'b0;
        
        #2
        WRITEREG = 3'd2;
        WRITEDATA = 8'd95;
        WRITEENABLE = 1'b1;
        
        #7
        WRITEENABLE = 1'b0;
        
        #1
        READREG1 = 3'd2;
        
        #7
        WRITEREG = 3'd1;
        WRITEDATA = 8'd28;
        WRITEENABLE = 1'b1;
        READREG1 = 3'd1;
        
        #8
        WRITEENABLE = 1'b0;
        
        #8
        WRITEREG = 3'd4;
        WRITEDATA = 8'd6;
        WRITEENABLE = 1'b1;
        
        #8
        WRITEDATA = 8'd15;
        WRITEENABLE = 1'b1;
        
        #10
        WRITEENABLE = 1'b0;
        
        #6
        WRITEREG = -3'd1;
        WRITEDATA = 8'd50;
        WRITEENABLE = 1'b1;
        
        #5
        WRITEENABLE = 1'b0;
        
        #10
        $finish;
    end
    
    // clock signal generation
    always
        #4 CLK = ~CLK;
        

endmodule

Part2/reg_file_wavedata.vcd
$date
	Wed May 10 11:03:20 2023
$end
$version
	Icarus Verilog
$end
$timescale
	1s
$end
$scope module reg_file_tb $end
$var wire 8 ! REGOUT2 [7:0] $end
$var wire 8 " REGOUT1 [7:0] $end
$var reg 1 # CLK $end
$var reg 3 $ READREG1 [2:0] $end
$var reg 3 % READREG2 [2:0] $end
$var reg 1 & RESET $end
$var reg 8 ' WRITEDATA [7:0] $end
$var reg 1 ( WRITEENABLE $end
$var reg 3 ) WRITEREG [2:0] $end
$scope module myregfile $end
$var wire 1 # CLK $end
$var wire 8 * IN [7:0] $end
$var wire 3 + INADDRESS [2:0] $end
$var wire 8 , OUT1 [7:0] $end
$var wire 3 - OUT1ADDRESS [2:0] $end
$var wire 8 . OUT2 [7:0] $end
$var wire 3 / OUT2ADDRESS [2:0] $end
$var wire 1 & RESET $end
$var wire 1 ( WRITE $end
$var integer 32 0 i [31:0] $end
$upscope $end
$upscope $end
$enddefinitions $end
$comment Show the parameter values. $end
$dumpall
$end
#0
$dumpvars
bx 0
bx /
bx .
bx -
bx ,
bx +
bx *
bx )
0(
bx '
0&
bx %
bx $
1#
bx "
bx !
$end
#4
0#
b100 %
b100 /
b0 $
b0 -
1&
#8
1#
#9
b1000 0
#10
0&
#11
b0 !
b0 .
b0 "
b0 ,
#12
1(
b1011111 '
b1011111 *
b10 )
b10 +
0#
#16
1#
#19
0(
#20
b10 $
b10 -
0#
#22
b1011111 "
b1011111 ,
#24
1#
#27
b1 $
b1 -
1(
b11100 '
b11100 *
b1 )
b1 +
#28
0#
#29
b0 "
b0 ,
#32
1#
#35
b11100 "
b11100 ,
0(
#36
0#
#40
1#
#43
1(
b110 '
b110 *
b100 )
b100 +
#44
0#
#48
1#
#51
b110 !
b110 .
b1111 '
b1111 *
#52
0#
#56
1#
#59
b1111 !
b1111 .
#60
0#
#61
0(
#64
1#
#67
1(
b110010 '
b110010 *
b111 )
b111 +
#68
0#
#72
1#
0(
