Part4/mux.v
/*
Authers     : WIJERATHNA I.M.K.D.I.     e19446@eng.pdn.ac.lk
              DISSANAYAKE D.M.I.G.      e19090@eng.pdn.ac.lk
Lab         : Lab 5 part 3
              mux.v
Last Updated: Tuesday, May 23, 2023 4:00:11 PM
*/

//tested - working properly
module mux(IN1,IN2,SELECT,OUT);

    //declaring ports
    input [7:0] IN1, IN2;   // 2 inputs
    input SELECT;           // select bit input
    output reg [7:0] OUT;   // output

    // always taking inputs and updating the regarding output accordingly
    always @(IN1,IN2,SELECT)

    begin
        //if select bit is low
        if (SELECT==1'b0)
            begin
                assign OUT = IN1;  //switch to IN1
            end
        // else select bit is high
        else
            begin
                assign OUT = IN2;  //switch to IN2
            end
    end

endmodule

/*

//test mux 
module stimulus;
    
    reg [7:0] IN1, IN2;   // 2 inputs
    reg SELECT;           // select bit input
    wire [7:0] OUT;        // output


    //calling mux module
    mux testmux(IN1,IN2,SELECT,OUT);

    initial begin
        IN1=8'b00001000;
        IN2=8'b00000001;
        SELECT=1'b1;
        
        $monitor("%d",OUT);

        #5
        SELECT=1'b0;
        #5
        SELECT=1'b1;
        

    end
endmodule


*/

Part4/twos_compliment.v
/*
Authers     : WIJERATHNA I.M.K.D.I.     e19446@eng.pdn.ac.lk
              DISSANAYAKE D.M.I.G.      e19090@eng.pdn.ac.lk
Lab         : Lab 5 part 3
              twos_compliment.v
Last Updated: Tuesday, May 23, 2023 4:25:00 PM
*/

module twos_compliment(IN,OUT);
    // declaring ports
    input [7:0] IN;
    output [7:0] OUT;

    // 2's complement operation
        //adding artificial delay of 1 second
        // Out = (fipping the bits in IN) + 1
    assign #1 OUT =(~IN)+1;

endmodule



/*

//test twos_compliment
module stimulus;

    reg [7:0] IN;
    wire [7:0] OUT;

    twos_compliment test_tc(IN,OUT);

    initial begin
        IN=8'b00001111;
        #5
        $display("%b",OUT);

    end
endmodule 
*/

Part3/reg_file.v
/*
Authers     : WIJERATHNA I.M.K.D.I.     e19446@eng.pdn.ac.lk
              DISSANAYAKE D.M.I.G.      e19090@eng.pdn.ac.lk
Lab         : Lab 5 part 2
              reg_file.v
Last Updated: Wednesday, May 10, 2023 10:27:08 AM
*/

// Register File module to store output values from ALU
module reg_file(IN,OUT1,OUT2,INADDRESS,OUT1ADDRESS,OUT2ADDRESS, WRITE, CLK, RESET) ;
   
    //declaring ports

    //data input ports
    input[7:0] IN;
    //data output ports
    output[7:0] OUT1;
    output[7:0] OUT2;
    // address ports
    input[2:0] INADDRESS;
    input[2:0] OUT1ADDRESS;
    input[2:0] OUT2ADDRESS;
    //control input ports
    input WRITE;
    // clock signal and reset signal
    input CLK;
    input RESET;
   

    //declaring a register array(8*8)
    reg[7:0] REGISTER[0:7];

    /* $$$$$$$$$$$$$$$$$$$$$$$$$$$$$$$$$$$$$$$$$$$$$$$$$$$$$$$$$$$$$$$$$$$$$$$$$$$$$$$$$$$$$$$
         REGISTER READING OPERATION 
         --------------------------

         1. Reading the values in REGISTER specified by the provided addresses asynchronously
         2. The values are loaded onto OUT1 and OUT2
         3. Artificial delays of two time  units (#2) included

       $$$$$$$$$$$$$$$$$$$$$$$$$$$$$$$$$$$$$$$$$$$$$$$$$$$$$$$$$$$$$$$$$$$$$$$$$$$$$$$$$$$$$$$$*/
    assign #2 OUT1 = REGISTER[OUT1ADDRESS];
    assign #2 OUT2 = REGISTER[OUT2ADDRESS];

    
    /* $$$$$$$$$$$$$$$$$$$$$$$$$$$$$$$$$$$$$$$$$$$$$$$$$$$$$$$$$$$$$$$$$$$$$$$$$$$$$$$$$$$$$$$
         REGISTER WRITING OPERATION 
         --------------------------

         1. Positive edge triggerd with the clock pulse synchronously
         2. If RESET is enabled reset all the values of the REGISTER
         3. Else if WRITEENABLE wirte the data values into the REGISTER

       $$$$$$$$$$$$$$$$$$$$$$$$$$$$$$$$$$$$$$$$$$$$$$$$$$$$$$$$$$$$$$$$$$$$$$$$$$$$$$$$$$$$$$$$*/
    
    integer i; //parameter to iterate through the REGISTER

    // begin the continous loop at the positive edge of a clock pulse
    always @(posedge CLK)
          begin
          // if RESET is enabled Reset all the values in REGISTER
          // (Replace all values in REGISTER by 0)
          if (RESET)
               begin
               #1 // Artificial delay of one time unit
               
               for (i=0;i<8;i=i+1)
                    begin
                    REGISTER[i]<=0;
                    end
               end

          //else if check WRITEENABLE
          // if it is enabled write data values
          else
               begin
               if (WRITE)
                    begin
                    #1 // Artificial delay of one time unit
                    REGISTER[INADDRESS] <= IN;
                    end
               end
          end
//end the module
endmodule

Part3/alu.v
/*
Authers     : WIJERATHNA I.M.K.D.I.     e19446@eng.pdn.ac.lk
              DISSANAYAKE D.M.I.G.      e19090@eng.pdn.ac.lk
Lab         : Lab 5 part 1
              alu_part1_group13.v
Last Updated: Tuesday, May 9, 2023 4:30:38 PM
*/

// function for FORWARD operation
module aluFORWARD(DATA2,RESULT); // start module
    // declaring ports
    input [7:0] DATA2;
    output [7:0] RESULT;
    // assigning the result and the delay
    assign #1 RESULT=DATA2;
endmodule                        // end module

// function for ADD operation
module aluADD(DATA1,DATA2,RESULT); // start module
    // declaring ports
    input [7:0] DATA1,DATA2;
    output [7:0] RESULT;
    // assigning the result and the delay
    assign #2 RESULT=DATA1+DATA2;
endmodule                        // end module

// function for AND operation
module aluAND(DATA1,DATA2,RESULT); // start module
    // declaring ports
    input [7:0] DATA1,DATA2;
    output [7:0] RESULT;
    // assigning the result and the delay
    assign #1 RESULT=DATA1&DATA2;
endmodule                        // end module

// function for OR operation
module aluOR(DATA1,DATA2,RESULT); // start module
    // declaring ports
    input [7:0] DATA1,DATA2;
    output [7:0] RESULT;
    // assigning the result and the delay
    assign #1 RESULT=DATA1|DATA2;
endmodule                        // end module

///////////////////////////////////////////////////////////////
// main module
module alu(DATA1, DATA2, RESULT, SELECT);
    //declaring ports
    input [7:0] DATA1,DATA2;
    input [2:0] SELECT; 
    //declaring output port register
    output reg [7:0] RESULT;
    //declaring wires
    wire [7:0]  ANS_FORWARD,ANS_ADD,ANS_AND,ANS_OR;

    // instantiating modules
    aluFORWARD f1(DATA2,ANS_FORWARD);
    aluADD f2(DATA1,DATA2,ANS_ADD);
    aluAND f3(DATA1,DATA2,ANS_AND);
    aluOR f4(DATA1,DATA2,ANS_OR);

    //
    always @(DATA1,DATA2,RESULT)
    begin
        // switch case 
        case(SELECT)
            3'b000:
                // IF (SELECT == 000)    => FORWARD
                assign RESULT=ANS_FORWARD;
            3'b001:
                // IF (SELECT == 001)    => ADD
                assign RESULT=ANS_ADD;
            3'b010:
                // IF (SELECT == 010)    => AND
                assign RESULT=ANS_AND;
            3'b011:
                // IF (SELECT == 011)    => OR
                assign RESULT=ANS_OR;
            default:
                // IF (SELECT == 1XX)    => no operations executed for now
                RESULT=8'b00000000;
        // end of switch case
        endcase
            
    end

endmodule


/*
//Test values   - Tested and properly functioning
module stimulus;
    reg [7:0] DATA1, DATA2;
    reg [2:0] SELECT;
    wire [7:0] RESULT;

    //calling the alu module
    alu alu1(DATA1,DATA2,RESULT,SELECT);

    initial begin
        //testing FORWARD operation
        DATA1 = 8'b00001001;    
        DATA2 = 8'b01100011;    
        SELECT = 3'b000;
        #5
        $display("%b FORWARD %b = %b", DATA1, DATA2, RESULT);

        //testing ADD operation
        DATA1 = 8'b10001111;
        DATA2 = 8'b00001001;
        SELECT = 3'b001;
        #2
        $display("%b   ADD   %b = %b", DATA1, DATA2, RESULT);

        //testing AND opertion 
        DATA1 = 8'b00001111;
        DATA2 = 8'b01011001;
        SELECT = 3'b010;
        #2
        $display("%b   AND   %b = %b", DATA1, DATA2, RESULT);

        //testing OR operation
        DATA1 = 8'b00001111;
        DATA2 = 8'b01111001;
        SELECT = 3'b011;
        #2
        $display("%b    OR   %b = %b", DATA1, DATA2, RESULT);
    end

endmodule

*/

Part6/pc_add.v
/*
Authers     : WIJERATHNA I.M.K.D.I.     e19446@eng.pdn.ac.lk
              DISSANAYAKE D.M.I.G.      e19090@eng.pdn.ac.lk
Lab         : Lab 5 part 3
              pc.v
Last Updated: Sunday, May 28, 2023 2:54:54 PM
*/

// tested - working properly
module pc_add(PC,PCADDED); 
    

    // declaring ports
    input [31:0] PC;    //initial PC value
    output reg [31:0] PCADDED;  //final PC value

    always @(PC) begin
    // assign PC_value +1 with 1 s  artificial delay
        #1 PCADDED=PC+4;
    end

endmodule

Part3/cpu.v
/*
Authers     : WIJERATHNA I.M.K.D.I.     e19446@eng.pdn.ac.lk
              DISSANAYAKE D.M.I.G.      e19090@eng.pdn.ac.lk
Lab         : Lab 5 part 3
              cpu.v
Last Updated: Wednesday, May 24, 2023 6:36:58 AM
*/

//including alu , register , mux , 2's compliment , Program counter
`include "alu.v"
`include "reg_file.v"
`include "mux.v"
`include "twos_compliment.v"
`include "pc_add.v"





// Register File module to store output values from ALU
module cpu(PC,INSTRUCTION, CLK, RESET) ;

    //////////////- Declaring ports -///////////////////
    //input Instruction
    input [31:0] INSTRUCTION;
    // clock signal and reset signal
    input CLK;
    input RESET;
    //Output port - program counter
    output reg [31:0] PC;
    //Current OPCODE for the CPU
    reg [7:0] OPCODE;
    /////////////////////////////////////////////////////

    //////////////- Declaring Connections to other modules -//////////////
    //  alu
    wire [7:0] DATA1,DATA2; // input operands to alu
    reg [2:0] ALUOP;       // select input to alu (for selecting operation)
    wire [7:0] ALURESULT;   // output from alu - Result

    // register file
    wire[2:0] WRITEREG;    // input address to register file
    /*                        output ALURESULT from alu as input to register file */
    wire[2:0] READREG1;    // output-1  address from register file
    wire[2:0] READREG2;    // output-2 address from register file
    wire[7:0] REGOUT2;     // output-2 from reg file
    /*                        output-1 from reg file REGOUT1[7:0] is DATA1 input to alu*/
    reg WRITEENABLE;       // Writeenable to reg file

    // immediate mux
    wire [7:0] IMMEDIATE;   // immediate value as input_1 to the immediate_mux
    wire [7:0] NEGMUXOUT;   // negation_mux output as input_2 to the immediate_mux
    /*OUTPUT                   output of the immediate mux is DATA2 input to the ALU */
    reg IMSELECT;           // Select bit input to the immediate_mux

    // negation mux
    wire [7:0] TWOSOUT  ;   // Output from the 2's compliment as input_1 to the negation_mux
    /*INPUT2                   REGOUT2[7:0] Output from the reg file as input_2 to the negation_mux */
    /*OUTPUT                   NEGMUXOUT[7:0] as the output from negation_mux */
    reg NEGSELECT;           // Select bit input to the negation mux

    // program counter
    wire [31:0] PCADDED;            // output from program_counter 
    

    //////////////////////////////////////////////////////////////////////////////////////////////////////


    //////////-Control Unit-Program Counter update-//////////////////////

    // program counter adder
    pc_add cpu_pc_add(PC,PCADDED);

    always @(posedge CLK) begin //always at the +ve edge of the clock pulse
      
        // if reset is high program counter value=>0
        if (RESET==1'b1)   begin 
        #1 PC =0;    //+1 time unit delay
        end
    end
    
    always @(posedge CLK) begin   // pc update
        #1 PC =PCADDED;           //+ 1 time unit delay
    end
    
    

    /////////////////////////////////////////////////////////////////////

    //assigning fields of instruction format
    /* |   Opcode   |   Rd    |    Rt    |  Rs/Imm  |   */

    assign WRITEREG=INSTRUCTION[23:16];  //Rd => destination register
    assign READREG1=INSTRUCTION[15:8];   //Rt => 1st operand register
    assign READREG2=INSTRUCTION[7:0];    //Rs => 2nd operand register
    assign IMMEDIATE=INSTRUCTION[7:0];   //immediate value register

    ////////////////////////////////////////////////////////////////////
    /////////////-Instruction Decoding-/////////////////////////////////

    always @(INSTRUCTION)   //decoding process occurs continuosly
    begin
        OPCODE=INSTRUCTION[31:24];       //Opcode field in the instruction format
        #1                              //adding 1 time unit delay

        case(OPCODE)
            //loadi 
            8'b00000000:	begin
                                ALUOP = 3'b000;			//Set alu to FORWARD
                                IMSELECT = 1'b1;		//Set immeiate_mux to select immediate value
                                NEGSELECT = 1'b0;		//Set neg_mux to select positive sign
                                WRITEENABLE = 1'b1;		//Enable writing to register
                            end
            
            //mov
			8'b00000001:	begin
								ALUOP = 3'b000;			//Set alu to FORWARD
								IMSELECT = 1'b0;		//Set imm_mux to select register i/p
								NEGSELECT = 1'b0;		//Set neg_mux to select positive sign
								WRITEENABLE = 1'b1;		//Enable writing to register
							end
            
            //add
			8'b00000010:	begin
								ALUOP = 3'b001;			//Set alu to ADD
								IMSELECT= 1'b0;		    //Set imm_mux to select register i/p
								NEGSELECT = 1'b0;		//Set neg_mux to select positive sign
								WRITEENABLE = 1'b1;		//Enable writing to register
							end	
		
			//sub 
			8'b00000011:	begin
								ALUOP = 3'b001;			//Set alu to ADD
								IMSELECT = 1'b0;		//Set imm_mux to select register input
								NEGSELECT = 1'b1;		//Set neg_mux to select negative sign
								WRITEENABLE = 1'b1;		//Enable writing to register
							end

			//and 
			8'b00000100:	begin
								ALUOP = 3'b010;			//Set alu to AND
								IMSELECT = 1'b0;		//Set imm_mux to select register input
								NEGSELECT = 1'b0;		//Set neg_mux to select positive sign
								WRITEENABLE = 1'b1;		//Enable writing to register
							end
							
			//or 
			8'b00000101:	begin
								ALUOP = 3'b011;			//Set ALU to OR
								IMSELECT = 1'b0;		//Set imm_mux to select register input
								NEGSELECT = 1'b0;		//Set neg_mux to select positive sign
								WRITEENABLE = 1'b1;		//Enable writing to register
							end
			
        endcase
    end

    ////////- calling all the cpu modules-////////////////


    //alu
    alu cpu_alu(DATA1,DATA2,ALURESULT,ALUOP);

    //register file
    reg_file cpu_reg_file(ALURESULT,DATA1,REGOUT2,WRITEREG,READREG1,READREG2,WRITEENABLE,CLK,RESET);

    // 2's compliment
    twos_compliment cpu_tc(REGOUT2,TWOSOUT);

    // Negation mux
    mux cpu_neg_mux(TWOSOUT,REGOUT2,NEGSELECT,NEGMUXOUT);

    // Immediate mux
    mux cpu_im_mux(NEGMUXOUT,IMMEDIATE,IMSELECT,DATA2);
endmodule

Part5/cpu_tb.v
// Computer Architecture (CO224) - Lab 05
// Design: Testbench of Integrated CPU of Simple Processor
// Author: Kisaru Liyanage

// tested - working properly//
module cpu_tb;

    reg CLK, RESET;
    wire [31:0] PC;
    wire [31:0] INSTRUCTION;
    
    /* 
    ------------------------
     SIMPLE INSTRUCTION MEM
    ------------------------
    */
    
    // TODO: Initialize an array of registers (8x1024) named 'instr_mem' to be used as instruction memory
	reg[7:0] instr_mem[0:1023];
	
    
    // TODO: Create combinational logic to support CPU instruction fetching, given the Program Counter(PC) value 
    //       (make sure you include the delay for instruction fetching here)
	assign #2 INSTRUCTION = {instr_mem[PC+3], instr_mem[PC+2], instr_mem[PC+1], instr_mem[PC]};
    
    initial
    begin
        // Initialize instruction memory with the set of instructions you need execute on CPU
        
        // METHOD 1: manually loading instructions to instr_mem
        //{instr_mem[10'd3], instr_mem[10'd2], instr_mem[10'd1], instr_mem[10'd0]} = 32'b00000000000001000000000000000101;
        //{instr_mem[10'd7], instr_mem[10'd6], instr_mem[10'd5], instr_mem[10'd4]} = 32'b00000000000000100000000000001001;
        //{instr_mem[10'd11], instr_mem[10'd10], instr_mem[10'd9], instr_mem[10'd8]} = 32'b00000010000001100000010000000010;
        
        // METHOD 2: loading instr_mem content from instr_mem.mem file
        $readmemb("instr_mem.mem", instr_mem);
    end
    
    /* 
    -----
     CPU
    -----
    */
    cpu mycpu(PC, INSTRUCTION, CLK, RESET);

    initial
    begin
    
        // generate files needed to plot the waveform using GTKWave
        $dumpfile("cpu_wavedata.vcd");
		$dumpvars(0, cpu_tb);
        
        CLK = 1'b0;
        RESET = 1'b1;
        
        // TODO: Reset the CPU (by giving a pulse to RESET signal) to start the program execution
		#5
		RESET = 1'b0;
        
        // finish simulation after some time
        #300
        $finish;
        
    end
    
    // clock signal generation
    always
        #4 CLK = ~CLK;
        

endmodule

Part3/cpu_wavedata.vcd
$date
	Wed May 31 09:54:05 2023
$end
$version
	Icarus Verilog
$end
$timescale
	1s
$end
$scope module cpu_tb $end
$var wire 32 ! PC [31:0] $end
$var wire 32 " INSTRUCTION [31:0] $end
$var reg 1 # CLK $end
$var reg 1 $ RESET $end
$scope module mycpu $end
$var wire 1 # CLK $end
$var wire 32 % INSTRUCTION [31:0] $end
$var wire 1 $ RESET $end
$var wire 3 & WRITEREG [2:0] $end
$var wire 8 ' TWOSOUT [7:0] $end
$var wire 8 ( REGOUT2 [7:0] $end
$var wire 3 ) READREG2 [2:0] $end
$var wire 3 * READREG1 [2:0] $end
$var wire 32 + PCADDED [31:0] $end
$var wire 8 , NEGMUXOUT [7:0] $end
$var wire 8 - IMMEDIATE [7:0] $end
$var wire 8 . DATA2 [7:0] $end
$var wire 8 / DATA1 [7:0] $end
$var wire 8 0 ALURESULT [7:0] $end
$var reg 3 1 ALUOP [2:0] $end
$var reg 1 2 IMSELECT $end
$var reg 1 3 NEGSELECT $end
$var reg 8 4 OPCODE [7:0] $end
$var reg 32 5 PC [31:0] $end
$var reg 1 6 WRITEENABLE $end
$scope module cpu_alu $end
$var wire 3 7 SELECT [2:0] $end
$var wire 8 8 DATA2 [7:0] $end
$var wire 8 9 DATA1 [7:0] $end
$var wire 8 : ANS_OR [7:0] $end
$var wire 8 ; ANS_FORWARD [7:0] $end
$var wire 8 < ANS_AND [7:0] $end
$var wire 8 = ANS_ADD [7:0] $end
$var reg 8 > RESULT [7:0] $end
$scope module f1 $end
$var wire 8 ? RESULT [7:0] $end
$var wire 8 @ DATA2 [7:0] $end
$upscope $end
$scope module f2 $end
$var wire 8 A RESULT [7:0] $end
$var wire 8 B DATA2 [7:0] $end
$var wire 8 C DATA1 [7:0] $end
$upscope $end
$scope module f3 $end
$var wire 8 D RESULT [7:0] $end
$var wire 8 E DATA2 [7:0] $end
$var wire 8 F DATA1 [7:0] $end
$upscope $end
$scope module f4 $end
$var wire 8 G RESULT [7:0] $end
$var wire 8 H DATA2 [7:0] $end
$var wire 8 I DATA1 [7:0] $end
$upscope $end
$upscope $end
$scope module cpu_im_mux $end
$var wire 8 J IN2 [7:0] $end
$var wire 1 2 SELECT $end
$var wire 8 K IN1 [7:0] $end
$var reg 8 L OUT [7:0] $end
$upscope $end
$scope module cpu_neg_mux $end
$var wire 1 3 SELECT $end
$var wire 8 M IN2 [7:0] $end
$var wire 8 N IN1 [7:0] $end
$var reg 8 O OUT [7:0] $end
$upscope $end
$scope module cpu_pc_add $end
$var wire 32 P PC [31:0] $end
$var reg 32 Q PCADDED [31:0] $end
$upscope $end
$scope module cpu_reg_file $end
$var wire 1 # CLK $end
$var wire 8 R IN [7:0] $end
$var wire 3 S INADDRESS [2:0] $end
$var wire 8 T OUT1 [7:0] $end
$var wire 3 U OUT1ADDRESS [2:0] $end
$var wire 8 V OUT2 [7:0] $end
$var wire 3 W OUT2ADDRESS [2:0] $end
$var wire 1 $ RESET $end
$var wire 1 6 WRITE $end
$var integer 32 X i [31:0] $end
$upscope $end
$scope module cpu_tc $end
$var wire 8 Y IN [7:0] $end
$var wire 8 Z OUT [7:0] $end
$upscope $end
$upscope $end
$upscope $end
$enddefinitions $end
$comment Show the parameter values. $end
$dumpall
$end
#0
$dumpvars
bx Z
bx Y
bx X
bx W
bx V
bx U
bx T
bx S
bx R
bx Q
bx P
bx O
bx N
bx M
bx L
bx K
bx J
bx I
bx H
bx G
bx F
bx E
bx D
bx C
bx B
bx A
bx @
bx ?
bx >
bx =
bx <
bx ;
bx :
bx 9
bx 8
bx 7
x6
bx 5
bx 4
x3
x2
bx 1
bx 0
bx /
bx .
bx -
bx ,
bx +
bx *
bx )
bx (
bx '
bx &
bx %
1$
0#
bx "
bx !
$end
#4
1#
#5
b1000 X
b0 !
b0 5
b0 P
0$
#6
b100 +
b100 Q
#7
b0 0
b0 >
b0 R
b0 &
b0 S
b0 *
b0 U
b101 )
b101 W
b101 .
b101 8
b101 @
b101 B
b101 E
b101 H
b101 L
b0 4
b101 -
b101 J
b101 "
b101 %
#8
bx1x1 :
bx1x1 G
b0x0x <
b0x0x D
b101 ;
b101 ?
16
03
12
b0 1
b0 7
0#
#9
b101 0
b101 >
b101 R
b0 /
b0 9
b0 C
b0 F
b0 I
b0 T
b0 (
b0 M
b0 V
b0 Y
#10
b101 :
b101 G
b0 <
b0 D
b0 ,
b0 K
b0 O
b0 '
b0 N
b0 Z
#11
b101 =
b101 A
#12
1#
#13
b100 !
b100 5
b100 P
#14
b1000 +
b1000 Q
#15
b1 &
b1 S
b1 )
b1 W
b1001 .
b1001 8
b1001 @
b1001 B
b1001 E
b1001 H
b1001 L
b1001 -
b1001 J
b101 /
b101 9
b101 C
b101 F
b101 I
b101 T
b10000000000001001 "
b10000000000001001 %
#16
b1101 :
b1101 G
b1 <
b1 D
b1001 0
b1001 >
b1001 R
b1001 ;
b1001 ?
0#
#17
b1110 =
b1110 A
#20
1#
#21
b1000 !
b1000 5
b1000 P
#22
b1100 +
b1100 Q
#23
b10 &
b10 S
b1 4
b1 .
b1 8
b1 @
b1 B
b1 E
b1 H
b1 L
b1 -
b1 J
b1001 (
b1001 M
b1001 V
b1001 Y
b1000000100000000000000001 "
b1000000100000000000000001 %
#24
b11110111 .
b11110111 8
b11110111 @
b11110111 B
b11110111 E
b11110111 H
b11110111 L
b101 :
b101 G
b11110111 ,
b11110111 K
b11110111 O
b11110111 '
b11110111 N
b11110111 Z
02
b1 0
b1 >
b1 R
b1 ;
b1 ?
0#
#25
b11110111 :
b11110111 G
b101 <
b101 D
b11110111 0
b11110111 >
b11110111 R
b11110111 ;
b11110111 ?
#26
b11111100 =
b11111100 A
#28
1#
#29
b1100 !
b1100 5
b1100 P
#30
b10000 +
b10000 Q
#31
b11 &
b11 S
b10 *
b10 U
b0 )
b0 W
b10 4
b0 -
b0 J
b10000000110000001000000000 "
b10000000110000001000000000 %
#32
b1 1
b1 7
0#
#33
b11111100 0
b11111100 >
b11111100 R
b11110111 /
b11110111 9
b11110111 C
b11110111 F
b11110111 I
b11110111 T
b101 (
b101 M
b101 V
b101 Y
#34
b11110111 <
b11110111 D
b11111011 .
b11111011 8
b11111011 @
b11111011 B
b11111011 E
b11111011 H
b11111011 L
b11111011 ,
b11111011 K
b11111011 O
b11111011 '
b11111011 N
b11111011 Z
#35
b11111111 :
b11111111 G
b11110011 <
b11110011 D
b11111011 ;
b11111011 ?
#36
b11110010 0
b11110010 >
b11110010 R
b11110010 =
b11110010 A
1#
#37
b10000 !
b10000 5
b10000 P
#38
b10100 +
b10100 Q
#39
b100 &
b100 S
b11 *
b11 U
b1 )
b1 W
b11 4
b1 -
b1 J
b11000001000000001100000001 "
b11000001000000001100000001 %
#40
b101 .
b101 8
b101 @
b101 B
b101 E
b101 H
b101 L
b101 ,
b101 K
b101 O
13
0#
#41
b11110111 :
b11110111 G
b101 <
b101 D
b101 ;
b101 ?
b11110010 /
b11110010 9
b11110010 C
b11110010 F
b11110010 I
b11110010 T
b1001 .
b1001 8
b1001 @
b1001 B
b1001 E
b1001 H
b1001 L
b1001 ,
b1001 K
b1001 O
b1001 (
b1001 M
b1001 V
b1001 Y
#42
b11110111 '
b11110111 N
b11110111 Z
b11111011 :
b11111011 G
b0 <
b0 D
b1001 ;
b1001 ?
#43
b11111011 0
b11111011 >
b11111011 R
b11111011 =
b11111011 A
#44
1#
#45
b10100 !
b10100 5
b10100 P
#46
b11000 +
b11000 Q
#47
b0 &
b0 S
b0 *
b0 U
b101 )
b101 W
b0 4
b1110101 -
b1110101 J
b1110101 "
b1110101 %
#48
b1001 0
b1001 >
b1001 R
b11110111 ,
b11110111 K
b11110111 O
b1110101 .
b1110101 8
b1110101 @
b1110101 B
b1110101 E
b1110101 H
b1110101 L
03
12
b0 1
b0 7
0#
#49
b11110111 :
b11110111 G
b1110000 <
b1110000 D
b1110101 0
b1110101 >
b1110101 R
b1110101 ;
b1110101 ?
b101 /
b101 9
b101 C
b101 F
b101 I
b101 T
b0 (
b0 M
b0 V
b0 Y
#50
b1110101 :
b1110101 G
b101 <
b101 D
b0 ,
b0 K
b0 O
b0 '
b0 N
b0 Z
#51
b1111010 =
b1111010 A
#52
1#
#53
b11000 !
b11000 5
b11000 P
#54
b11100 +
b11100 Q
#55
b1 &
b1 S
b10 )
b10 W
b10010010 .
b10010010 8
b10010010 @
b10010010 B
b10010010 E
b10010010 H
b10010010 L
b10010010 -
b10010010 J
b1110101 /
b1110101 9
b1110101 C
b1110101 F
b1110101 I
b1110101 T
b10000000010010010 "
b10000000010010010 %
#56
b11110111 :
b11110111 G
b10000 <
b10000 D
b10010010 0
b10010010 >
b10010010 R
b10010010 ;
b10010010 ?
0#
#57
b11110111 (
b11110111 M
b11110111 V
b11110111 Y
b111 =
b111 A
#58
b1001 ,
b1001 K
b1001 O
b1001 '
b1001 N
b1001 Z
#60
1#
#61
b11100 !
b11100 5
b11100 P
#62
b100000 +
b100000 Q
#63
b101 &
b101 S
b1 *
b1 U
b0 )
b0 W
b100 4
b0 .
b0 8
b0 @
b0 B
b0 E
b0 H
b0 L
b0 -
b0 J
b100000001010000000100000000 "
b100000001010000000100000000 %
#64
b1001 .
b1001 8
b1001 @
b1001 B
b1001 E
b1001 H
b1001 L
b1110101 :
b1110101 G
b0 <
b0 D
02
b10 1
b10 7
b0 0
b0 >
b0 R
b0 ;
b0 ?
0#
#65
b1111101 :
b1111101 G
b1 0
b1 >
b1 R
b1 <
b1 D
b1001 ;
b1001 ?
b10010010 /
b10010010 9
b10010010 C
b10010010 F
b10010010 I
b10010010 T
b1110101 (
b1110101 M
b1110101 V
b1110101 Y
#66
b10011011 :
b10011011 G
b0 0
b0 >
b0 R
b0 <
b0 D
b10001011 .
b10001011 8
b10001011 @
b10001011 B
b10001011 E
b10001011 H
b10001011 L
b10001011 ,
b10001011 K
b10001011 O
b10001011 '
b10001011 N
b10001011 Z
#67
b10000010 0
b10000010 >
b10000010 R
b10000010 <
b10000010 D
b10001011 ;
b10001011 ?
#68
b11101 =
b11101 A
1#
#69
b100000 !
b100000 5
b100000 P
#70
b100100 +
b100100 Q
#71
b110 &
b110 S
b101 *
b101 U
b10 )
b10 W
b101 4
b10 -
b10 J
b101000001100000010100000010 "
b101000001100000010100000010 %
#72
b11 1
b11 7
0#
#73
b10011011 0
b10011011 >
b10011011 R
b10000010 /
b10000010 9
b10000010 C
b10000010 F
b10000010 I
b10000010 T
b11110111 (
b11110111 M
b11110111 V
b11110111 Y
#74
b10001011 0
b10001011 >
b10001011 R
b10001011 :
b10001011 G
b1001 .
b1001 8
b1001 @
b1001 B
b1001 E
b1001 H
b1001 L
b1001 ,
b1001 K
b1001 O
b1001 '
b1001 N
b1001 Z
#75
b0 <
b0 D
b1001 ;
b1001 ?
#76
b10001011 =
b10001011 A
1#
#77
b100100 !
b100100 5
b100100 P
#78
b101000 +
b101000 Q
#79
bx &
bx S
bx *
bx U
bx )
bx W
bx 4
bx -
bx J
bx "
bx %
#80
0#
#81
bx /
bx 9
bx C
bx F
bx I
bx T
bx (
bx M
bx V
bx Y
#82
bx1xx1 0
bx1xx1 >
bx1xx1 R
bx1xx1 :
bx1xx1 G
b0x00x <
b0x00x D
bx .
bx 8
bx @
bx B
bx E
bx H
bx L
bx ,
bx K
bx O
bx '
bx N
bx Z
#83
bx 0
bx >
bx R
bx :
bx G
bx <
bx D
bx ;
bx ?
bx =
bx A
#84
1#
#85
b101000 !
b101000 5
b101000 P
#86
b101100 +
b101100 Q
#88
0#
#92
1#
#93
b101100 !
b101100 5
b101100 P
#94
b110000 +
b110000 Q
#96
0#
#100
1#
#101
b110000 !
b110000 5
b110000 P
#102
b110100 +
b110100 Q
#104
0#
#108
1#
#109
b110100 !
b110100 5
b110100 P
#110
b111000 +
b111000 Q
#112
0#
#116
1#
#117
b111000 !
b111000 5
b111000 P
#118
b111100 +
b111100 Q
#120
0#
#124
1#
#125
b111100 !
b111100 5
b111100 P
#126
b1000000 +
b1000000 Q
#128
0#
#132
1#
#133
b1000000 !
b1000000 5
b1000000 P
#134
b1000100 +
b1000100 Q
#136
0#
#140
1#
#141
b1000100 !
b1000100 5
b1000100 P
#142
b1001000 +
b1001000 Q
#144
0#
#148
1#
#149
b1001000 !
b1001000 5
b1001000 P
#150
b1001100 +
b1001100 Q
#152
0#
#156
1#
#157
b1001100 !
b1001100 5
b1001100 P
#158
b1010000 +
b1010000 Q
#160
0#
#164
1#
#165
b1010000 !
b1010000 5
b1010000 P
#166
b1010100 +
b1010100 Q
#168
0#
#172
1#
#173
b1010100 !
b1010100 5
b1010100 P
#174
b1011000 +
b1011000 Q
#176
0#
#180
1#
#181
b1011000 !
b1011000 5
b1011000 P
#182
b1011100 +
b1011100 Q
#184
0#
#188
1#
#189
b1011100 !
b1011100 5
b1011100 P
#190
b1100000 +
b1100000 Q
#192
0#
#196
1#
#197
b1100000 !
b1100000 5
b1100000 P
#198
b1100100 +
b1100100 Q
#200
0#
#204
1#
#205
b1100100 !
b1100100 5
b1100100 P
#206
b1101000 +
b1101000 Q
#208
0#
#212
1#
#213
b1101000 !
b1101000 5
b1101000 P
#214
b1101100 +
b1101100 Q
#216
0#
#220
1#
#221
b1101100 !
b1101100 5
b1101100 P
#222
b1110000 +
b1110000 Q
#224
0#
#228
1#
#229
b1110000 !
b1110000 5
b1110000 P
#230
b1110100 +
b1110100 Q
#232
0#
#236
1#
#237
b1110100 !
b1110100 5
b1110100 P
#238
b1111000 +
b1111000 Q
#240
0#
#244
1#
#245
b1111000 !
b1111000 5
b1111000 P
#246
b1111100 +
b1111100 Q
#248
0#
#252
1#
#253
b1111100 !
b1111100 5
b1111100 P
#254
b10000000 +
b10000000 Q
#256
0#
#260
1#
#261
b10000000 !
b10000000 5
b10000000 P
#262
b10000100 +
b10000100 Q
#264
0#
#268
1#
#269
b10000100 !
b10000100 5
b10000100 P
#270
b10001000 +
b10001000 Q
#272
0#
#276
1#
#277
b10001000 !
b10001000 5
b10001000 P
#278
b10001100 +
b10001100 Q
#280
0#
#284
1#
#285
b10001100 !
b10001100 5
b10001100 P
